rdjohns_file/Write_log.py
rdjohns_file/__init__.py
rdjohns_file/search_directory.py
rdjohns_file-0.0.5.dist-info/LICENSE
rdjohns_file-0.0.5.dist-info/METADATA
rdjohns_file-0.0.5.dist-info/WHEEL
rdjohns_file-0.0.5.dist-info/top_level.txt
rdjohns_file-0.0.5.dist-info/RECORD
