Metadata-Version: 2.1
Name: rdjohns-file
Version: 0.0.5
Summary: search all directory available and list it in the array
Home-page: https://github.com/RDJohns/rdjohns_file
Author: David Johns
Author-email: rakotonindrianajohns@email.com
Classifier: Programming Language :: Python :: 3
Classifier: License :: OSI Approved :: MIT License
Classifier: Operating System :: OS Independent
License-File: LICENSE
